rename_kicad_project/__init__.py
rename_kicad_project/__main__.py
rename_kicad_project/cli.py
rename_kicad_project/logger.py
rename_kicad_project/manipulator.py
rename_kicad_project-1.1.0.dist-info/METADATA
rename_kicad_project-1.1.0.dist-info/entry_points.txt
rename_kicad_project-1.1.0.dist-info/WHEEL
rename_kicad_project-1.1.0.dist-info/LICENSE
rename_kicad_project-1.1.0.dist-info/RECORD
