Metadata-Version: 2.1
Name: rename-kicad-project
Version: 1.1.0
Summary: A nifty tool for renaming or cloning your KiCad project.
Home-page: https://github.com/likeablob/rename-kicad-project
License: MIT
Keywords: kicad
Author: likeablob
Author-email: 46628917+likeablob@users.noreply.github.com
Requires-Python: >=3.7,<4.0
Classifier: License :: OSI Approved :: MIT License
Classifier: Programming Language :: Python :: 3
Classifier: Programming Language :: Python :: 3.7
Classifier: Programming Language :: Python :: 3.8
Classifier: Programming Language :: Python :: 3.9
Classifier: Programming Language :: Python :: 3.10
Classifier: Programming Language :: Python :: 3.11
Requires-Dist: pyproject-flake8 (>=0.0.1-alpha.2,<0.0.2)
Requires-Dist: rich (>=10.16.0,<11.0.0)
Requires-Dist: typer[all] (>=0.4.0,<0.5.0)
Requires-Dist: typing-extensions (>=4.0.1,<5.0.0)
Project-URL: Repository, https://github.com/likeablob/rename-kicad-project.git
